LICENSE
MANIFEST.in
README.md
requirements.txt
setup.cfg
setup.py
lml_lab3/__init__.py
lml_lab3/lml_lab3.py
lml_lab3.egg-info/PKG-INFO
lml_lab3.egg-info/SOURCES.txt
lml_lab3.egg-info/dependency_links.txt
lml_lab3.egg-info/not-zip-safe
lml_lab3.egg-info/top_level.txt